DFN_Py_Tools/__init__.py
DFN_Py_Tools/__version__.py
DFN_Py_Tools/dfn_math.py
DFN_Py_Tools-0.1.0.dist-info/LICENSE
DFN_Py_Tools-0.1.0.dist-info/METADATA
DFN_Py_Tools-0.1.0.dist-info/WHEEL
DFN_Py_Tools-0.1.0.dist-info/top_level.txt
DFN_Py_Tools-0.1.0.dist-info/RECORD
